{"FUNDID":"600054","actionErrors":[],"actionMessages":[],"errorMessages":[],"errors":{},"fieldErrors":{},"inMonth":"201712","inYear":"2017","indexCode":null,"isPagination":"false","jsonCallBack":"","list":[],"locale":"zh_CN","pageHelp":{"beginPage":1,"cacheSize":5,"data":null,"endDate":null,"endPage":null,"objectResult":null,"pageCount":null,"pageNo":1,"pageSize":10,"searchDate":null,"sort":null,"startDate":null,"total":0},"prodType":"","productId":"","result":[{"change":0.78,"changeData":0.11,"closeMarketValue":732479.1,"closeNegoValue":732479.1,"closePrice":14.27,"closeProfitRate":30.29,"closeTrAmt":2876.38,"closeTrTx":0.2,"closeTrVol":202.44,"closeTxDate":"2017-12-29","evgAmt":0.0,"evgPrice":14.209,"evgVol":0.0,"id":"600054","last_close_price":14.16,"maxHighPrice":14.31,"maxHighPriceDate":"2017-12-29","maxTrAmt":2876.38,"maxTrAmtDate":"2017-12-29","maxTrVol":202.44,"maxTrVolDate":"2017-12-29","minLowPrice":14.15,"minLowPriceDate":"","minTrAmt":0.0,"minTrAmtDate":"2017-12-29","minTrVol":0.0,"minTrVolDate":"","openPrice":14.19,"openTxDate":"2017-12-29","productName":"黄山旅游","totalAmt":2876.38,"totalChange":1.13,"totalExchRate":0.3944,"totalPrice":2.8764458047E7,"totalTx":0.2,"totalTxDate":0.0,"totalVol":202.44},{"change":2.59,"changeData":0.0,"closeMarketValue":732479.1,"closeNegoValue":732479.1,"closePrice":14.27,"closeProfitRate":30.29,"closeTrAmt":0.0,"closeTrTx":0.0,"closeTrVol":0.0,"closeTxDate":"201712","evgAmt":3567.07,"evgPrice":0.0,"evgVol":253.42,"id":"600054","last_close_price":13.91,"maxHighPrice":14.5,"maxHighPriceDate":"2017-12-27","maxTrAmt":6090.57,"maxTrAmtDate":"2017-12-22","maxTrVol":436.02,"maxTrVolDate":"2017-12-05","minLowPrice":13.48,"minLowPriceDate":"2017-12-05","minTrAmt":1418.08,"minTrAmtDate":"2017-12-15","minTrVol":101.66,"minTrVolDate":"2017-12-15","openPrice":13.96,"openTxDate":null,"productName":"黄山旅游","totalAmt":74908.38,"totalChange":7.57,"totalExchRate":10.37,"totalPrice":0.0,"totalTx":5.52,"totalTxDate":21.0,"totalVol":5321.79},{"change":0.0,"changeData":0.0,"closeMarketValue":0.0,"closeNegoValue":0.0,"closePrice":0.0,"closeProfitRate":0.0,"closeTrAmt":0.0,"closeTrTx":0.0,"closeTrVol":0.0,"closeTxDate":null,"evgAmt":0.0,"evgPrice":0.0,"evgVol":0.0,"id":"","last_close_price":0.0,"maxHighPrice":0.0,"maxHighPriceDate":"","maxTrAmt":0.0,"maxTrAmtDate":"","maxTrVol":0.0,"maxTrVolDate":"","minLowPrice":0.0,"minLowPriceDate":"","minTrAmt":0.0,"minTrAmtDate":"","minTrVol":0.0,"minTrVolDate":"","openPrice":0.0,"openTxDate":null,"productName":"","totalAmt":0.0,"totalChange":0.0,"totalExchRate":0.0,"totalPrice":0.0,"totalTx":0.0,"totalTxDate":0.0,"totalVol":0.0},{"change":-51.44,"changeData":0.0,"closeMarketValue":520486.2,"closeNegoValue":520486.2,"closePrice":10.14,"closeProfitRate":18.3006,"closeTrAmt":3104.3224,"closeTrTx":0.4693,"closeTrVol":306.4657,"closeTxDate":"2018-11-22","evgAmt":0.0,"evgPrice":16.613104739262145,"evgVol":0.0,"id":"600054","last_close_price":6.02,"maxHighPrice":33.39,"maxHighPriceDate":"2008-01-02","maxTrAmt":47323.4,"maxTrAmtDate":"1997-05-06","maxTrVol":2272.76,"maxTrVolDate":"2018-05-31","minLowPrice":5.9,"minLowPriceDate":"2003-11-07","minTrAmt":22.41,"minTrAmtDate":"2003-08-19","minTrVol":2.81,"minTrVolDate":"2003-08-19","openPrice":20.88,"openTxDate":"1997-05-06","productName":"黄山旅游","totalAmt":1.780707416E7,"totalChange":465.93,"totalExchRate":9767.34809999999,"totalPrice":1.7807070061567682E11,"totalTx":1114.85,"totalTxDate":0.0,"totalVol":1071868.89}],"searchDate":"2017-12-29","texts":null,"type":null,"validateCode":""}