{"FUNDID":"600197","actionErrors":[],"actionMessages":[],"errorMessages":[],"errors":{},"fieldErrors":{},"inMonth":"201812","inYear":"2018","indexCode":null,"isPagination":"false","jsonCallBack":"","list":[],"locale":"en_US","pageHelp":{"beginPage":1,"cacheSize":5,"data":null,"endDate":null,"endPage":null,"objectResult":null,"pageCount":null,"pageNo":1,"pageSize":10,"searchDate":null,"sort":null,"startDate":null,"total":0},"prodType":"","productId":"","result":[{"change":0.0,"changeData":0.0,"closeMarketValue":0.0,"closeNegoValue":0.0,"closePrice":0.0,"closeProfitRate":0.0,"closeTrAmt":0.0,"closeTrTx":0.0,"closeTrVol":0.0,"closeTxDate":null,"evgAmt":0.0,"evgPrice":0.0,"evgVol":0.0,"id":"","last_close_price":0.0,"maxHighPrice":0.0,"maxHighPriceDate":"","maxTrAmt":0.0,"maxTrAmtDate":"","maxTrVol":0.0,"maxTrVol1":"0","maxTrVolDate":"","minLowPrice":0.0,"minLowPriceDate":"","minTrAmt":0.0,"minTrAmtDate":"","minTrVol":0.0,"minTrVol1":"0","minTrVolDate":"","openPrice":0.0,"openTxDate":null,"productName":"","productType":null,"totalAmt":0.0,"totalChange":0.0,"totalExchRate":0.0,"totalPrice":0.0,"totalTx":0.0,"totalTxDate":0.0,"totalVol":0.0,"totalVol1":"0"},{"change":-7.98,"changeData":0.0,"closeMarketValue":574623.0,"closeNegoValue":574623.0,"closePrice":13.03,"closeProfitRate":16.26,"closeTrAmt":0.0,"closeTrTx":0.0,"closeTrVol":0.0,"closeTxDate":"201812","evgAmt":10769.33,"evgPrice":0.0,"evgVol":769.85,"id":"600197","last_close_price":14.16,"maxHighPrice":15.0,"maxHighPriceDate":"2018-12-03","maxTrAmt":29474.88,"maxTrAmtDate":"2018-12-03","maxTrVol":2006.12,"maxTrVol1":"0","maxTrVolDate":"2018-12-03","minLowPrice":12.63,"minLowPriceDate":"2018-12-28","minTrAmt":4884.96,"minTrAmtDate":"2018-12-24","minTrVol":371.44,"minTrVol1":"0","minTrVolDate":"2018-12-24","openPrice":14.57,"openTxDate":null,"productName":"伊力特","productType":null,"totalAmt":215386.55,"totalChange":18.77,"totalExchRate":34.91,"totalPrice":0.0,"totalTx":15.5,"totalTxDate":20.0,"totalVol":15396.92,"totalVol1":"0"},{"change":-43.3,"changeData":0.0,"closeMarketValue":574623.0,"closeNegoValue":574623.0,"closePrice":13.03,"closeProfitRate":16.26,"closeTrAmt":0.0,"closeTrTx":0.0,"closeTrVol":0.0,"closeTxDate":"201812","evgAmt":332671.27,"evgPrice":0.0,"evgVol":16814.01,"id":"600197","last_close_price":23.42,"maxHighPrice":30.0,"maxHighPriceDate":"2018-01-22","maxTrAmt":62542.45,"maxTrAmtDate":"2018-06-05","maxTrVol":2559.06,"maxTrVol1":"0","maxTrVolDate":"2018-06-05","minLowPrice":11.95,"minLowPriceDate":"2018-10-30","minTrAmt":4884.96,"minTrAmtDate":"2018-12-24","minTrVol":300.95,"minTrVol1":"0","minTrVolDate":"2018-01-11","openPrice":23.41,"openTxDate":null,"productName":"伊力特","productType":null,"totalAmt":3992055.29,"totalChange":145.9,"totalExchRate":457.52,"totalPrice":0.0,"totalTx":247.26,"totalTxDate":12.0,"totalVol":201768.17,"totalVol1":"0"},{"change":0.0,"changeData":0.0,"closeMarketValue":651801.41,"closeNegoValue":651801.41,"closePrice":14.78,"closeProfitRate":15.233,"closeTrAmt":5017.0366,"closeTrTx":0.3965,"closeTrVol":338.7727,"closeTxDate":"2019-11-29","evgAmt":0.0,"evgPrice":13.301132657245114,"evgVol":0.0,"id":"600197","last_close_price":6.26,"maxHighPrice":30.0,"maxHighPriceDate":"2018-01-22","maxTrAmt":63974.58,"maxTrAmtDate":"2015-12-15","maxTrVol":4851.83,"maxTrVol1":"0","maxTrVolDate":"2006-12-15","minLowPrice":0.0,"minLowPriceDate":"","minTrAmt":0.0,"minTrAmtDate":"1999-09-14","minTrVol":0.0,"minTrVol1":"0","minTrVolDate":"1999-09-14","openPrice":0.0,"openTxDate":"1999-09-14","productName":"伊力特","productType":null,"totalAmt":4.02082396E7,"totalChange":0.0,"totalExchRate":10023.218000000032,"totalPrice":4.0208201169165436E11,"totalTx":2444.32,"totalTxDate":0.0,"totalVol":3022915.58,"totalVol1":"0"}],"searchDate":"2018-12-31","texts":null,"type":null,"validateCode":""}