{"FUNDID":"600588","actionErrors":[],"actionMessages":[],"errorMessages":[],"errors":{},"fieldErrors":{},"inMonth":"201712","inYear":"2017","indexCode":null,"isPagination":"false","jsonCallBack":"","list":[],"locale":"zh_CN","pageHelp":{"beginPage":1,"cacheSize":5,"data":null,"endDate":null,"endPage":null,"objectResult":null,"pageCount":null,"pageNo":1,"pageSize":10,"searchDate":null,"sort":null,"startDate":null,"total":0},"prodType":"","productId":"","result":[{"change":2.42,"changeData":0.5,"closeMarketValue":3096820.67,"closeNegoValue":3047798.67,"closePrice":21.15,"closeProfitRate":156.89,"closeTrAmt":10500.8,"closeTrTx":0.65,"closeTrVol":498.56,"closeTxDate":"2017-12-29","evgAmt":0.0,"evgPrice":21.062,"evgVol":0.0,"id":"600588","last_close_price":20.65,"maxHighPrice":21.28,"maxHighPriceDate":"2017-12-29","maxTrAmt":10500.8,"maxTrAmtDate":"2017-12-29","maxTrVol":498.56,"maxTrVolDate":"2017-12-29","minLowPrice":20.67,"minLowPriceDate":"","minTrAmt":0.0,"minTrAmtDate":"2017-12-29","minTrVol":0.0,"minTrVolDate":"","openPrice":20.67,"openTxDate":"2017-12-29","productName":"用友网络","totalAmt":10500.8,"totalChange":2.95,"totalExchRate":0.346,"totalPrice":1.05006054278E8,"totalTx":0.65,"totalTxDate":0.0,"totalVol":498.56},{"change":3.22,"changeData":0.0,"closeMarketValue":3096820.67,"closeNegoValue":3047798.67,"closePrice":21.15,"closeProfitRate":156.89,"closeTrAmt":0.0,"closeTrTx":0.0,"closeTrVol":0.0,"closeTxDate":"201712","evgAmt":14358.89,"evgPrice":0.0,"evgVol":675.67,"id":"600588","last_close_price":20.49,"maxHighPrice":22.45,"maxHighPriceDate":"2017-12-19","maxTrAmt":39260.24,"maxTrAmtDate":"2017-12-11","maxTrVol":1837.33,"maxTrVolDate":"2017-12-11","minLowPrice":19.13,"minLowPriceDate":"2017-12-06","minTrAmt":6948.88,"minTrAmtDate":"2017-12-07","minTrVol":352.06,"minTrVolDate":"2017-12-07","openPrice":20.49,"openTxDate":null,"productName":"用友网络","totalAmt":301536.67,"totalChange":17.36,"totalExchRate":9.85,"totalPrice":0.0,"totalTx":15.95,"totalTxDate":21.0,"totalVol":14189.17},{"change":0.0,"changeData":0.0,"closeMarketValue":0.0,"closeNegoValue":0.0,"closePrice":0.0,"closeProfitRate":0.0,"closeTrAmt":0.0,"closeTrTx":0.0,"closeTrVol":0.0,"closeTxDate":null,"evgAmt":0.0,"evgPrice":0.0,"evgVol":0.0,"id":"","last_close_price":0.0,"maxHighPrice":0.0,"maxHighPriceDate":"","maxTrAmt":0.0,"maxTrAmtDate":"","maxTrVol":0.0,"maxTrVolDate":"","minLowPrice":0.0,"minLowPriceDate":"","minTrAmt":0.0,"minTrAmtDate":"","minTrVol":0.0,"minTrVolDate":"","openPrice":0.0,"openTxDate":null,"productName":"","totalAmt":0.0,"totalChange":0.0,"totalExchRate":0.0,"totalPrice":0.0,"totalTx":0.0,"totalTxDate":0.0,"totalVol":0.0},{"change":0.0,"changeData":0.0,"closeMarketValue":4747611.29,"closeNegoValue":4707693.55,"closePrice":24.78,"closeProfitRate":122.0209,"closeTrAmt":31994.0792,"closeTrTx":1.6285,"closeTrVol":1284.4171,"closeTxDate":"2018-11-22","evgAmt":0.0,"evgPrice":26.604453181519077,"evgVol":0.0,"id":"600588","last_close_price":36.68,"maxHighPrice":100.0,"maxHighPriceDate":"2001-05-18","maxTrAmt":646024.7,"maxTrAmtDate":"2015-07-22","maxTrVol":14041.95,"maxTrVolDate":"2015-07-22","minLowPrice":0.0,"minLowPriceDate":"","minTrAmt":0.0,"minTrAmtDate":"2001-05-15","minTrVol":0.0,"minTrVolDate":"2001-05-15","openPrice":0.0,"openTxDate":"2001-05-15","productName":"用友网络","totalAmt":1.0383412926E8,"totalChange":0.0,"totalExchRate":5624.221300000003,"totalPrice":1.0383406219080658E12,"totalTx":3489.04,"totalTxDate":0.0,"totalVol":3902882.78}],"searchDate":"2017-12-29","texts":null,"type":null,"validateCode":""}