{"FUNDID":"603993","actionErrors":[],"actionMessages":[],"errorMessages":[],"errors":{},"fieldErrors":{},"inMonth":"201612","inYear":"2016","indexCode":null,"isPagination":"false","jsonCallBack":"","list":[],"locale":"zh_CN","pageHelp":{"beginPage":1,"cacheSize":5,"data":null,"endDate":null,"endPage":null,"objectResult":null,"pageCount":null,"pageNo":1,"pageSize":10,"searchDate":null,"sort":null,"startDate":null,"total":0},"prodType":"","productId":"","result":[{"change":-0.53,"changeData":-0.02,"closeMarketValue":4818787.82,"closeNegoValue":4818787.82,"closePrice":3.72,"closeProfitRate":82.54,"closeTrAmt":7327.32,"closeTrTx":0.81,"closeTrVol":1966.87,"closeTxDate":"2016-12-30","evgAmt":0.0,"evgPrice":3.725,"evgVol":0.0,"id":"603993","last_close_price":3.74,"maxHighPrice":3.76,"maxHighPriceDate":"2016-12-30","maxTrAmt":7327.32,"maxTrAmtDate":"2016-12-30","maxTrVol":1966.87,"maxTrVolDate":"2016-12-30","minLowPrice":3.71,"minLowPriceDate":"","minTrAmt":0.0,"minTrAmtDate":"2016-12-30","minTrVol":0.0,"minTrVolDate":"","openPrice":3.74,"openTxDate":"2016-12-30","productName":"洛阳钼业","totalAmt":7327.32,"totalChange":1.35,"totalExchRate":0.1518,"totalPrice":7.3265859075E7,"totalTx":0.81,"totalTxDate":0.0,"totalVol":1966.87},{"change":-8.6,"changeData":0.0,"closeMarketValue":4818787.82,"closeNegoValue":4818787.82,"closePrice":3.72,"closeProfitRate":82.54,"closeTrAmt":0.0,"closeTrTx":0.0,"closeTrVol":0.0,"closeTxDate":"201612","evgAmt":11977.13,"evgPrice":0.0,"evgVol":3042.97,"id":"603993","last_close_price":4.07,"maxHighPrice":4.15,"maxHighPriceDate":"2016-12-08","maxTrAmt":25626.44,"maxTrAmtDate":"2016-12-07","maxTrVol":6320.58,"maxTrVolDate":"2016-12-07","minLowPrice":3.71,"minLowPriceDate":"2016-12-30","minTrAmt":5915.16,"minTrAmtDate":"2016-12-28","minTrVol":1559.45,"minTrVolDate":"2016-12-28","openPrice":4.08,"openTxDate":null,"productName":"洛阳钼业","totalAmt":263496.78,"totalChange":11.86,"totalExchRate":5.17,"totalPrice":0.0,"totalTx":22.7,"totalTxDate":22.0,"totalVol":66945.36},{"change":-16.03,"changeData":0.0,"closeMarketValue":4818787.82,"closeNegoValue":4818787.82,"closePrice":3.72,"closeProfitRate":82.54,"closeTrAmt":0.0,"closeTrTx":0.0,"closeTrVol":0.0,"closeTxDate":"201612","evgAmt":566103.29,"evgPrice":0.0,"evgVol":141202.38,"id":"603993","last_close_price":4.46,"maxHighPrice":4.9,"maxHighPriceDate":"2016-07-07","maxTrAmt":197598.87,"maxTrAmtDate":"2016-06-02","maxTrVol":44117.46,"maxTrVolDate":"2016-06-02","minLowPrice":3.04,"minLowPriceDate":"2016-01-28","minTrAmt":4193.63,"minTrAmtDate":"2016-09-20","minTrVol":1093.79,"minTrVolDate":"2016-09-20","openPrice":4.47,"openTxDate":null,"productName":"洛阳钼业","totalAmt":6793239.44,"totalChange":61.18,"totalExchRate":130.81,"totalPrice":0.0,"totalTx":582.74,"totalTxDate":12.0,"totalVol":1694428.51},{"change":-53.33,"changeData":0.0,"closeMarketValue":7172303.67,"closeNegoValue":7172303.67,"closePrice":4.06,"closeProfitRate":32.1482,"closeTrAmt":24789.3972,"closeTrTx":1.9656,"closeTrVol":6074.4774,"closeTxDate":"2018-11-22","evgAmt":0.0,"evgPrice":6.96338355069777,"evgVol":0.0,"id":"603993","last_close_price":3.0,"maxHighPrice":19.61,"maxHighPriceDate":"2015-06-05","maxTrAmt":536448.68,"maxTrAmtDate":"2017-09-12","maxTrVol":63408.51,"maxTrVolDate":"2017-09-12","minLowPrice":3.04,"minLowPriceDate":"2016-01-28","minTrAmt":781.21,"minTrAmtDate":"2014-04-24","minTrVol":142.26,"minTrVolDate":"2014-04-24","openPrice":8.7,"openTxDate":"2012-10-09","productName":"洛阳钼业","totalAmt":8.30454104E7,"totalChange":545.07,"totalExchRate":3894.2094000000056,"totalPrice":8.304540336725989E11,"totalTx":4929.15,"totalTxDate":0.0,"totalVol":1.192601309E7}],"searchDate":"2016-12-30","texts":null,"type":null,"validateCode":""}