{"actionErrors":[],"actionMessages":[],"errorMessages":[],"errors":{},"fieldErrors":{},"isPagination":"false","jsonCallBack":"","locale":"zh_CN","pageHelp":{"beginPage":1,"cacheSize":5,"data":null,"endDate":null,"endPage":null,"objectResult":null,"pageCount":null,"pageNo":1,"pageSize":10,"searchDate":null,"sort":null,"startDate":null,"total":0},"result":[{"DIVIDEND_PER_SHARE1_A":"0.0095","DIVIDEND_PER_SHARE2_A":"0.01","SECURITY_NAME_A":"太原重工","TOTAL_DIVIDEND_A":"-","SECURITY_CODE_A":"600169","COMPANY_CODE":"600169","A_SHARES":"-","EX_DIVIDEND_DATE_A":"2014-07-31","OPEN_PRICE_A":"3.63","FULL_NAME":"太原重工股份有限公司","LAST_CLOSE_PRICE_A":"3.51","ISS_VOL":"242395.5","RECORD_DATE_A":"2014-07-30"},{"DIVIDEND_PER_SHARE1_A":"0.005","DIVIDEND_PER_SHARE2_A":"0.05","SECURITY_NAME_A":"太原重工","TOTAL_DIVIDEND_A":"-","SECURITY_CODE_A":"600169","COMPANY_CODE":"600169","A_SHARES":"-","EX_DIVIDEND_DATE_A":"2011-06-07","OPEN_PRICE_A":"9.5","FULL_NAME":"太原重工股份有限公司","LAST_CLOSE_PRICE_A":"9.44","ISS_VOL":"80798.5","RECORD_DATE_A":"2011-06-03"},{"DIVIDEND_PER_SHARE1_A":"0.005","DIVIDEND_PER_SHARE2_A":"0.05","SECURITY_NAME_A":"太原重工","TOTAL_DIVIDEND_A":"-","SECURITY_CODE_A":"600169","COMPANY_CODE":"600169","A_SHARES":"-","EX_DIVIDEND_DATE_A":"2009-05-25","OPEN_PRICE_A":"14.11","FULL_NAME":"太原重工股份有限公司","LAST_CLOSE_PRICE_A":"14.83","ISS_VOL":"44677.2425","RECORD_DATE_A":"2009-05-22"},{"DIVIDEND_PER_SHARE1_A":"0.024","DIVIDEND_PER_SHARE2_A":"0.03","SECURITY_NAME_A":"太原重工","TOTAL_DIVIDEND_A":"-","SECURITY_CODE_A":"600169","COMPANY_CODE":"600169","A_SHARES":"-","EX_DIVIDEND_DATE_A":"2001-06-26","OPEN_PRICE_A":"9.68","FULL_NAME":"太原重工股份有限公司","LAST_CLOSE_PRICE_A":"9.65","ISS_VOL":"37217.2425","RECORD_DATE_A":"2001-06-25"}],"sqlId":"COMMON_SSE_ZQPZ_GG_LYFP_AGFH_L","texts":null,"type":"","validateCode":""}