{"actionErrors":[],"actionMessages":[],"errorMessages":[],"errors":{},"fieldErrors":{},"isPagination":"false","jsonCallBack":"","locale":"en_US","pageHelp":{"beginPage":1,"cacheSize":5,"data":null,"endDate":null,"endPage":null,"objectResult":null,"pageCount":null,"pageNo":1,"pageSize":10,"searchDate":null,"sort":null,"startDate":null,"total":0},"result":[{"EX_DIVIDEND_DATE_A":"2019-05-29","LAST_CLOSE_PRICE_A":"4.66","A_SHARES":"-","TOTAL_DIVIDEND_A":"-","SECURITY_NAME_A":"宁波港","SECURITY_CODE_A":"601018","RECORD_DATE_A":"2019-05-28","DIVIDEND_PER_SHARE1_A":"0.093","DIVIDEND_PER_SHARE2_A":"0.093","OPEN_PRICE_A":"4.64","COMPANY_CODE":"601018","FULL_NAME":"宁波舟山港股份有限公司","ISS_VOL":"1317284.7809"},{"EX_DIVIDEND_DATE_A":"2018-06-07","LAST_CLOSE_PRICE_A":"4.95","A_SHARES":"-","TOTAL_DIVIDEND_A":"-","SECURITY_NAME_A":"宁波港","SECURITY_CODE_A":"601018","RECORD_DATE_A":"2018-06-06","DIVIDEND_PER_SHARE1_A":"0.075","DIVIDEND_PER_SHARE2_A":"0.075","OPEN_PRICE_A":"4.98","COMPANY_CODE":"601018","FULL_NAME":"宁波舟山港股份有限公司","ISS_VOL":"1317284.7809"},{"EX_DIVIDEND_DATE_A":"2017-06-16","LAST_CLOSE_PRICE_A":"5.56","A_SHARES":"-","TOTAL_DIVIDEND_A":"-","SECURITY_NAME_A":"宁波港","SECURITY_CODE_A":"601018","RECORD_DATE_A":"2017-06-15","DIVIDEND_PER_SHARE1_A":"0.068","DIVIDEND_PER_SHARE2_A":"0.068","OPEN_PRICE_A":"5.57","COMPANY_CODE":"601018","FULL_NAME":"宁波舟山港股份有限公司","ISS_VOL":"1317284.7809"},{"EX_DIVIDEND_DATE_A":"2016-06-08","LAST_CLOSE_PRICE_A":"5.37","A_SHARES":"-","TOTAL_DIVIDEND_A":"-","SECURITY_NAME_A":"宁波港","SECURITY_CODE_A":"601018","RECORD_DATE_A":"2016-06-07","DIVIDEND_PER_SHARE1_A":"0.085","DIVIDEND_PER_SHARE2_A":"0.085","OPEN_PRICE_A":"5.39","COMPANY_CODE":"601018","FULL_NAME":"宁波舟山港股份有限公司","ISS_VOL":"1280000"},{"EX_DIVIDEND_DATE_A":"2015-05-22","LAST_CLOSE_PRICE_A":"10.11","A_SHARES":"-","TOTAL_DIVIDEND_A":"-","SECURITY_NAME_A":"宁波港","SECURITY_CODE_A":"601018","RECORD_DATE_A":"2015-05-21","DIVIDEND_PER_SHARE1_A":"0.0798","DIVIDEND_PER_SHARE2_A":"0.084","OPEN_PRICE_A":"11.12","COMPANY_CODE":"601018","FULL_NAME":"宁波舟山港股份有限公司","ISS_VOL":"1280000"},{"EX_DIVIDEND_DATE_A":"2014-06-26","LAST_CLOSE_PRICE_A":"2.21","A_SHARES":"-","TOTAL_DIVIDEND_A":"-","SECURITY_NAME_A":"宁波港","SECURITY_CODE_A":"601018","RECORD_DATE_A":"2014-06-25","DIVIDEND_PER_SHARE1_A":"0.07885","DIVIDEND_PER_SHARE2_A":"0.083","OPEN_PRICE_A":"2.22","COMPANY_CODE":"601018","FULL_NAME":"宁波舟山港股份有限公司","ISS_VOL":"1280000"},{"EX_DIVIDEND_DATE_A":"2013-06-19","LAST_CLOSE_PRICE_A":"2.26","A_SHARES":"-","TOTAL_DIVIDEND_A":"-","SECURITY_NAME_A":"宁波港","SECURITY_CODE_A":"601018","RECORD_DATE_A":"2013-06-18","DIVIDEND_PER_SHARE1_A":"0.08265","DIVIDEND_PER_SHARE2_A":"0.087","OPEN_PRICE_A":"2.28","COMPANY_CODE":"601018","FULL_NAME":"宁波舟山港股份有限公司","ISS_VOL":"1280000"},{"EX_DIVIDEND_DATE_A":"2012-07-06","LAST_CLOSE_PRICE_A":"2.46","A_SHARES":"-","TOTAL_DIVIDEND_A":"-","SECURITY_NAME_A":"宁波港","SECURITY_CODE_A":"601018","RECORD_DATE_A":"2012-07-05","DIVIDEND_PER_SHARE1_A":"0.0594","DIVIDEND_PER_SHARE2_A":"0.066","OPEN_PRICE_A":"2.48","COMPANY_CODE":"601018","FULL_NAME":"宁波舟山港股份有限公司","ISS_VOL":"1280000"},{"EX_DIVIDEND_DATE_A":"2011-07-04","LAST_CLOSE_PRICE_A":"3.17","A_SHARES":"-","TOTAL_DIVIDEND_A":"-","SECURITY_NAME_A":"宁波港","SECURITY_CODE_A":"601018","RECORD_DATE_A":"2011-07-01","DIVIDEND_PER_SHARE1_A":"0.027","DIVIDEND_PER_SHARE2_A":"0.03","OPEN_PRICE_A":"3.18","COMPANY_CODE":"601018","FULL_NAME":"宁波舟山港股份有限公司","ISS_VOL":"1280000"}],"sqlId":"COMMON_SSE_ZQPZ_GG_LYFP_AGFH_L","texts":null,"type":"","validateCode":""}