{"companyCode":"601158","isPagination":"true","jsonCallBack":"","pageHelp":{"beginPage":1,"cacheSize":1,"data":[{"AShares":480000,"BShares":0,"ROWNUM_":null,"changeReason":"77","changeReasonDesc":"有限售条件流通股上市","realDate":"2013-04-01","seq":5471931,"totalShares":480000},{"AShares":50000,"BShares":0,"ROWNUM_":null,"changeReason":"71","changeReasonDesc":"一般法人配售上市","realDate":"2010-06-30","seq":4138240,"totalShares":480000},{"AShares":27500,"BShares":0,"ROWNUM_":null,"changeReason":"31","changeReasonDesc":"A股新上市","realDate":"2010-03-29","seq":4019441,"totalShares":480000}],"endDate":null,"endPage":5,"objectResult":null,"pageCount":1,"pageNo":1,"pageSize":50,"searchDate":null,"sort":null,"startDate":null,"total":3},"result":[{"AShares":480000,"BShares":0,"ROWNUM_":null,"changeReason":"77","changeReasonDesc":"有限售条件流通股上市","realDate":"2013-04-01","seq":5471931,"totalShares":480000},{"AShares":50000,"BShares":0,"ROWNUM_":null,"changeReason":"71","changeReasonDesc":"一般法人配售上市","realDate":"2010-06-30","seq":4138240,"totalShares":480000},{"AShares":27500,"BShares":0,"ROWNUM_":null,"changeReason":"31","changeReasonDesc":"A股新上市","realDate":"2010-03-29","seq":4019441,"totalShares":480000}],"seq":""}